readables/__init__.py
readables/annotations.py
readables/env.py
readables/syncable.py
readables/dlock/__init__.py
readables/dlock/awaitable/__init__.py
readables/dlock/awaitable/core.py
readables/dlock/awaitable/state_manager.py
readables/dlock/awaitable/state_manager_tck.py
readables/dlock/blocking/__init__.py
readables/dlock/blocking/core.py
readables/dlock/blocking/state_manager.py
readables/dlock/blocking/state_manager_tck.py
readables_py-0.2.3.dist-info/licenses/LICENSE
readables_py-0.2.3.dist-info/METADATA
readables_py-0.2.3.dist-info/WHEEL
readables_py-0.2.3.dist-info/top_level.txt
readables_py-0.2.3.dist-info/RECORD
