Metadata-Version: 2.4
Name: readables-py
Version: 0.2.3
Summary: Add readability and self-documentation to Python code
License-Expression: Apache-2.0
Requires-Python: >=3.9
License-File: LICENSE
Provides-Extra: build
Requires-Dist: setuptools; extra == "build"
Dynamic: license-file
